beets_gdplaylists-0.2.14.dist-info/licenses/LICENSE
beetsplug/gdplaylists/__init__.py
beetsplug/gdplaylists/gdplex.py
beetsplug/gdplaylists/__pycache__/__init__.cpython-310.pyc
beetsplug/gdplaylists/__pycache__/gdplex.cpython-310.pyc
beetsplug/gdplaylists/playlists/1969-11-02.yml
beetsplug/gdplaylists/playlists/1969-12-26.yml
beetsplug/gdplaylists/playlists/1970-01-02.yml
beetsplug/gdplaylists/playlists/1970-01-03.yml
beetsplug/gdplaylists/playlists/1970-10-24.yml
beetsplug/gdplaylists/playlists/1971-04-12.yml
beetsplug/gdplaylists/playlists/1971-04-13.yml
beetsplug/gdplaylists/playlists/1971-11-20.yml
beetsplug/gdplaylists/playlists/1971-12-09.yml
beetsplug/gdplaylists/playlists/1971-12-10.yml
beetsplug/gdplaylists/playlists/1972-03-22.yml
beetsplug/gdplaylists/playlists/1972-03-23.yml
beetsplug/gdplaylists/playlists/1972-04-24.yml
beetsplug/gdplaylists/playlists/1972-05-24.yml
beetsplug/gdplaylists/playlists/1972-09-03.yml
beetsplug/gdplaylists/playlists/1972-09-09.yml
beetsplug/gdplaylists/playlists/1972-09-19.yml
beetsplug/gdplaylists/playlists/1972-10-17.yml
beetsplug/gdplaylists/playlists/1972-10-18.yml
beetsplug/gdplaylists/playlists/1972-10-19.yml
beetsplug/gdplaylists/playlists/1973-03-24.yml
beetsplug/gdplaylists/playlists/1973-03-26.yml
beetsplug/gdplaylists/playlists/1973-03-31.yml
beetsplug/gdplaylists/playlists/1973-06-22.yml
beetsplug/gdplaylists/playlists/1973-06-24.yml
beetsplug/gdplaylists/playlists/1973-06-26.yml
beetsplug/gdplaylists/playlists/1973-09-07.yml
beetsplug/gdplaylists/playlists/1973-09-08.yml
beetsplug/gdplaylists/playlists/1973-10-29.yml
beetsplug/gdplaylists/playlists/1973-10-30.yml
beetsplug/gdplaylists/playlists/1974-02-22.yml
beetsplug/gdplaylists/playlists/1974-02-23.yml
beetsplug/gdplaylists/playlists/1974-05-17.yml
beetsplug/gdplaylists/playlists/1974-05-19.yml
beetsplug/gdplaylists/playlists/1974-05-21.yml
beetsplug/gdplaylists/playlists/1974-06-22.yml
beetsplug/gdplaylists/playlists/1974-06-23.yml
beetsplug/gdplaylists/playlists/1976-10-02.yml
beets_gdplaylists-0.2.14.dist-info/METADATA
beets_gdplaylists-0.2.14.dist-info/WHEEL
beets_gdplaylists-0.2.14.dist-info/top_level.txt
beets_gdplaylists-0.2.14.dist-info/RECORD
