Metadata-Version: 2.4
Name: beets-gdplaylists
Version: 0.2.14
Summary: beets plugin to create Grateful Dead playlists
Author-email: Ross Hendry <rhendry@gmail.com>
Project-URL: Repository, https://github.com/chooban/beets-gogd
Keywords: beets,grateful dead,plex,playlists
Platform: ALL
Classifier: Topic :: Multimedia :: Sound/Audio
Classifier: License :: OSI Approved :: MIT License
Classifier: Environment :: Console
Classifier: Programming Language :: Python :: 3
License-File: LICENSE
Requires-Dist: beets>=1.6.0
Requires-Dist: plexapi>=4.15.0
Requires-Dist: pyyaml>=6
Requires-Dist: python-slugify>=7
Provides-Extra: dev
Requires-Dist: musicbrainzngs>=0.7.0; extra == "dev"
Dynamic: license-file
Dynamic: platform
Dynamic: requires-dist
